res/__init__.py
res/constants.py
res/mainapp.py
res/tools.py
res/views.py
tests/__init__.py
tests/test_time.py
unixtime_converter-1.0.3.dist-info/METADATA
unixtime_converter-1.0.3.dist-info/WHEEL
unixtime_converter-1.0.3.dist-info/entry_points.txt
unixtime_converter-1.0.3.dist-info/top_level.txt
unixtime_converter-1.0.3.dist-info/RECORD
