Metadata-Version: 2.1
Name: unixtime-converter
Version: 1.0.3
Summary: Unixtime converter
Home-page: https://docs.roadrunnerserver.com/unixtime/html/index.html
Author: Franz Wiesinger
Author-email: Franz Wiesinger <py@roadrunnerserver.com>
Maintainer-email: Franz Wiesinger <py@roadrunnerserver.com>
License: MIT license
Project-URL: Repository, https://github.com/WiesingF/UnixtimeConverter
Project-URL: Changelog, https://github.com/WiesingF/UnixtimeConverter/blob/main/changes.rst
Project-URL: Homepage, https://www.roadrunnerserver.com/
Project-URL: Documentation, https://docs.roadrunnerserver.com/unixtime/html/index.html
Keywords: unixtime,utc,local time,the epoch,converter,tkinter,GUI,timezone,datetime
Classifier: Environment :: X11 Applications
Classifier: Environment :: Win32 (MS Windows)
Classifier: Intended Audience :: Customer Service
Classifier: Intended Audience :: Developers
Classifier: Intended Audience :: System Administrators
Classifier: Intended Audience :: Information Technology
Classifier: License :: OSI Approved :: MIT License
Classifier: Natural Language :: English
Classifier: Programming Language :: Python :: 3.0
Classifier: Topic :: Desktop Environment
Classifier: Topic :: Software Development
Classifier: Topic :: Utilities
Requires-Python: > 3.7
Requires-Dist: datetime
Requires-Dist: pytz
Requires-Dist: tkhtmlview
Requires-Dist: zoneinfo
Provides-Extra: gui
Requires-Dist: tkinter ; extra == 'gui'
